Assn1/FullAdder.v
`timescale 1ns/1ns

module FA_Struct(a, b, cin, cout, sum);
 input  a, b, cin;      // inputs
 output cout, sum;      // output
 wire   w1, w2, w3, w4; // internal nets

 xor U1  (w1, a, b);
 xor U2  (sum, w1, cin);
 and U3  (w2, cin, w1);
 and U4  (w3, a, b);
 or  U6  (cout, w2, w3);
endmodule

// Truth Table
//      a   b   cin sum cout
//      0   0   0   0   0
//      0   0   1   1   0
//      0   1   0   1   0
//      0   1   1   0   1
//      1   0   0   1   0
//      1   0   1   0   1
//      1   1   0   0   1
//      1   1   1   1   1

Assn1/Part1/FullAdder_tb.v
/*
Assignment 1
Problem no: 1b
Semester: 5th
Group: 28
Members: 
Aryan Singh (19CS30007)
Abhinandan De (19CS10069)
*/

`timescale 1ns/1ns
`include "FullAdder.v"

module FullAdder_tb;
    reg a,b,cin;
    wire sum,cout;
    FA_Struct FA(a,b,cin,cout,sum);

    initial begin
        $dumpfile("FullAdder_tb.vcd");
        $dumpvars(0,FullAdder_tb);


        a=0;b=0;cin=0;#20;
        a=0;b=0;cin=1;#20;
        a=0;b=1;cin=0;#20;
        a=0;b=1;cin=1;#20;
        a=1;b=0;cin=0;#20;
        a=1;b=0;cin=1;#20;
        a=1;b=1;cin=0;#20;
        a=1;b=1;cin=1;#20;
        
        $display("end of test.");
end

endmodule

Assn1/FullAdder_tb.vcd
$date
	Sun Aug 22 16:39:25 2021
$end
$version
	Icarus Verilog
$end
$timescale
	1ns
$end
$scope module FullAdder_tb $end
$var wire 1 ! sum $end
$var wire 1 " cout $end
$var reg 1 # a $end
$var reg 1 $ b $end
$var reg 1 % cin $end
$scope module FA $end
$var wire 1 # a $end
$var wire 1 $ b $end
$var wire 1 % cin $end
$var wire 1 " cout $end
$var wire 1 ! sum $end
$var wire 1 & w1 $end
$var wire 1 ' w2 $end
$var wire 1 ( w3 $end
$upscope $end
$upscope $end
$enddefinitions $end
#0
$dumpvars
0(
0'
0&
0%
0$
0#
0"
0!
$end
#20
1!
1%
#40
1&
0%
1$
#60
1"
0!
1'
1%
#80
0"
1!
0'
0%
0$
1#
#100
1"
0!
1'
1%
#120
0'
0&
1(
0%
1$
#140
1!
1%
